observability_mtl_instrument/__init__.py
observability_mtl_instrument/logs/builders/fullLogBase.py
observability_mtl_instrument/logs/builders/fullLogConfig.py
observability_mtl_instrument/logs/builders/fullLogConfigAsync.py
observability_mtl_instrument/logs/log_config.py
observability_mtl_instrument/logs/request_strategies/log_request.py
observability_mtl_instrument/logs/request_strategies/log_request_interface.py
observability_mtl_instrument/metrics/metric_config.py
observability_mtl_instrument/tracer/trace_config.py
observability_mtl_instrument-0.2.1.dist-info/LICENSE
observability_mtl_instrument-0.2.1.dist-info/METADATA
observability_mtl_instrument-0.2.1.dist-info/WHEEL
observability_mtl_instrument-0.2.1.dist-info/RECORD
