Metadata-Version: 2.1
Name: observability-mtl-instrument
Version: 0.2.1
Summary: 
License: MIT
Author: SergioNascimento07
Author-email: sergioricjr7@gmail.com
Requires-Python: >=3.10,<4.0
Classifier: Development Status :: 5 - Production/Stable
Classifier: Intended Audience :: Developers
Classifier: License :: OSI Approved :: MIT License
Classifier: Natural Language :: Portuguese (Brazilian)
Classifier: Programming Language :: Python :: 3
Classifier: Programming Language :: Python :: 3.10
Classifier: Programming Language :: Python :: 3.11
Classifier: Programming Language :: Python :: 3.12
Classifier: Topic :: System :: Monitoring
Requires-Dist: httpx (>=0.25.2,<0.26.0)
Requires-Dist: opentelemetry-exporter-otlp-proto-http (>=1.21.0,<2.0.0)
Requires-Dist: opentelemetry-instrumentation-logging (>=0.42b0,<0.43)
Requires-Dist: opentelemetry-sdk (>=1.21.0,<2.0.0)
Requires-Dist: prometheus-client (>=0.19.0,<0.20.0)
Requires-Dist: pytz (>=2023.3.post1,<2024.0)
Project-URL: Bug Tracker, https://github.com/SergioRicJr/observability-mtl-instrument/issues
Project-URL: Código, https://github.com/SergioRicJr/observability-mtl-instrument
Project-URL: Documentação, https://observability-mtl-instrument.readthedocs.io/pt-br/latest/
